web3rpc/__init__.py
web3rpc/valid.py
web3rpc-2.1.0.dist-info/METADATA
web3rpc-2.1.0.dist-info/WHEEL
web3rpc-2.1.0.dist-info/top_level.txt
web3rpc-2.1.0.dist-info/RECORD
