Metadata-Version: 2.1
Name: web3rpc
Version: 2.1.0
Summary: Tools for Web3
Author: web3rpcs
Classifier: Programming Language :: Python :: 3
Classifier: License :: OSI Approved :: MIT License
Classifier: Operating System :: OS Independent
Requires-Python: >=3.6
